MANIFEST.in
README.md
setup.py
Python_Spoke.egg-info/PKG-INFO
Python_Spoke.egg-info/SOURCES.txt
Python_Spoke.egg-info/dependency_links.txt
Python_Spoke.egg-info/requires.txt
Python_Spoke.egg-info/top_level.txt
spoke/__init__.py