Metadata-Version: 1.0
Name: Python-Spoke
Version: 1.0.0
Summary: API bindings for Spoke API
Home-page: https://github.com/Threadless/python-spoke
Author: Rob Hoelz
Author-email: rob.hoelz@skinnycorp.com
License: MIT
Keywords: spoke
Platform: UNKNOWN
